Bjob.py
bjob-1.0.0.dist-info/METADATA
bjob-1.0.0.dist-info/WHEEL
bjob-1.0.0.dist-info/entry_points.txt
bjob-1.0.0.dist-info/top_level.txt
bjob-1.0.0.dist-info/RECORD
