Metadata-Version: 2.4
Name: Bjob
Version: 1.0.0
Summary: 工作性价比计算器 - MCP工具
Project-URL: Homepage, https://github.com/yourusername/Bjob
Project-URL: Issues, https://github.com/yourusername/Bjob/issues
Classifier: Programming Language :: Python :: 3
Classifier: License :: OSI Approved :: MIT License
Classifier: Operating System :: OS Independent
Requires-Python: >=3.8
Requires-Dist: mcp>=1.0.0
Requires-Dist: fastmcp>=0.4.0
